{
  "version": "4.2.10",
  "flags": {},
  "shapes": [
    {
      "label": "Defect",
      "points": [
        [
          129.14285714285714,
          89.28571428571429
        ],
        [
          126.57142857142857,
          94.14285714285714
        ],
        [
          112.0,
          93.0
        ],
        [
          111.42857142857143,
          99.0
        ],
        [
          120.28571428571429,
          105.57142857142858
        ],
        [
          122.28571428571429,
          112.14285714285714
        ],
        [
          120.28571428571429,
          114.71428571428572
        ],
        [
          32.0,
          65.57142857142857
        ],
        [
          41.42857142857143,
          62.71428571428571
        ],
        [
          44.285714285714285,
          48.42857142857143
        ],
        [
          45.42857142857143,
          43.57142857142857
        ],
        [
          98.28571428571429,
          69.85714285714286
        ]
      ],
      "group_id": null,
      "shape_type": "polygon",
      "flags": {}
    }
  ],
  "imagePath": "..\\im\\62.jpg",
  "imageData": null,
  "imageHeight": 200,
  "imageWidth": 200
}